moneyFlowIndicator/__init__.py
moneyFlowIndicator/moneyFlowIndicatorPkg.py
moneyFlowIndicator-0.0.2.dist-info/LICENSE
moneyFlowIndicator-0.0.2.dist-info/METADATA
moneyFlowIndicator-0.0.2.dist-info/WHEEL
moneyFlowIndicator-0.0.2.dist-info/top_level.txt
moneyFlowIndicator-0.0.2.dist-info/RECORD
