Metadata-Version: 2.1
Name: moneyFlowIndicator
Version: 0.0.2
Summary: Institutional money flow
Home-page: https://github.com/pstrito/InstitutionalPip.git
Author: Example Author
Author-email: author@example.com
License: UNKNOWN
Platform: UNKNOWN
Classifier: Programming Language :: Python :: 3
Classifier: License :: OSI Approved :: MIT License
Classifier: Operating System :: OS Independent
License-File: LICENSE
